example/__init__.py
example/run.py
flask_celery/__init__.py
flask_celery/model.py
flask_celery_context-0.0.1.20040717.dist-info/LICENSE
flask_celery_context-0.0.1.20040717.dist-info/METADATA
flask_celery_context-0.0.1.20040717.dist-info/WHEEL
flask_celery_context-0.0.1.20040717.dist-info/top_level.txt
flask_celery_context-0.0.1.20040717.dist-info/RECORD
