Metadata-Version: 2.1
Name: flask-celery-context
Version: 0.0.1.20040717
Summary: 实现celery在flask下的上下文一致性的简单扩展
Home-page: https://github.com/BingerYang/flask_celery_context
Author: binger
Author-email: <xuehen_521@126.com>
Maintainer: binger
Maintainer-email: <xuehen_521@126.com>
License: UNKNOWN
Platform: all
Requires-Python: >=3.4
